agent_farm/__init__.py
agent_farm/macros.sql
agent_farm/main.py
agent_farm/py.typed
agent_farm-0.1.5.dist-info/WHEEL
agent_farm-0.1.5.dist-info/entry_points.txt
agent_farm-0.1.5.dist-info/METADATA
agent_farm-0.1.5.dist-info/RECORD
