Metadata-Version: 2.3
Name: agent-farm
Version: 0.1.5
Summary: DuckDB-powered MCP Server with SQL macros for LLM agents
Keywords: duckdb,mcp,llm,ollama,sql,agent
Author: Björn Bethge
Author-email: Björn Bethge <bjoern.bethge@gmail.com>
License: MIT
Classifier: Development Status :: 3 - Alpha
Classifier: Intended Audience :: Developers
Classifier: License :: OSI Approved :: MIT License
Classifier: Programming Language :: Python :: 3
Classifier: Programming Language :: Python :: 3.11
Classifier: Programming Language :: Python :: 3.12
Classifier: Topic :: Database
Classifier: Topic :: Scientific/Engineering :: Artificial Intelligence
Requires-Dist: duckdb>=1.1.0
Requires-Dist: pytest>=8.0 ; extra == 'dev'
Requires-Dist: ruff>=0.4 ; extra == 'dev'
Requires-Python: >=3.11
Project-URL: Homepage, https://github.com/bjoernbethge/agent-farm
Project-URL: Repository, https://github.com/bjoernbethge/agent-farm
Provides-Extra: dev
